{
  "lastUpdated": "2025-06-18T07:37:49.313Z",
  "status": "Active Developer",
  "today": {
    "codingMinutes": 65,
    "primaryLanguage": "Svelte",
    "environment": {
      "editor": "Neovim",
      "os": "Linux"
    }
  },
  "weeklyStats": {
    "totalHoursLast7Days": "18.3",
    "activeDaysCount": 7,
    "dailyAverageMinutes": 157,
    "languages": {
      "primary": "Svelte",
      "secondary": "TypeScript",
      "primaryPercentage": "47.8",
      "secondaryPercentage": "16.9"
    },
    "consistency": "High"
  }
}