{
  "lastUpdated": "2025-06-19T09:39:40.779Z",
  "status": "Active Developer",
  "today": {
    "codingMinutes": 99,
    "primaryLanguage": "Svelte",
    "environment": {
      "editor": "Neovim",
      "os": "Linux"
    }
  },
  "weeklyStats": {
    "totalHoursLast7Days": "20.5",
    "activeDaysCount": 7,
    "dailyAverageMinutes": 176,
    "languages": {
      "primary": "Svelte",
      "secondary": "TypeScript",
      "primaryPercentage": "66.0",
      "secondaryPercentage": "9.0"
    },
    "consistency": "High"
  }
}